LiquidDiffract/LiquidDiffract.py
LiquidDiffract/__init__.py
LiquidDiffract/version.py
LiquidDiffract/core/__init__.py
LiquidDiffract/core/core.py
LiquidDiffract/core/data_utils.py
LiquidDiffract/core/peak_fit.py
LiquidDiffract/gui/__init__.py
LiquidDiffract/gui/bkg_ui.py
LiquidDiffract/gui/main_widget.py
LiquidDiffract/gui/optim_ui.py
LiquidDiffract/gui/plot_widgets.py
LiquidDiffract/gui/results_ui.py
LiquidDiffract/gui/structure_ui.py
LiquidDiffract/gui/utility.py
LiquidDiffract/resources/__init__.py
LiquidDiffract/resources/form_factors.npy
LiquidDiffract/resources/mass_data.npy
LiquidDiffract/resources/pt_data.npy
LiquidDiffract/resources/docs/4_and_25_iterations.png
LiquidDiffract/resources/docs/LiquidDiffract v1.1.6-dev_refinement_tab.png
LiquidDiffract/resources/docs/__init__.py
LiquidDiffract/resources/docs/chi_squared_minimum_map.png
LiquidDiffract/resources/docs/fitting_region.png
LiquidDiffract/resources/docs/optimal_n_iter.png
LiquidDiffract/resources/hubbel_compton/Ac.npy
LiquidDiffract/resources/hubbel_compton/Ag.npy
LiquidDiffract/resources/hubbel_compton/Al.npy
LiquidDiffract/resources/hubbel_compton/Am.npy
LiquidDiffract/resources/hubbel_compton/Ar.npy
LiquidDiffract/resources/hubbel_compton/As.npy
LiquidDiffract/resources/hubbel_compton/At.npy
LiquidDiffract/resources/hubbel_compton/Au.npy
LiquidDiffract/resources/hubbel_compton/B.npy
LiquidDiffract/resources/hubbel_compton/Ba.npy
LiquidDiffract/resources/hubbel_compton/Be.npy
LiquidDiffract/resources/hubbel_compton/Bi.npy
LiquidDiffract/resources/hubbel_compton/Bk.npy
LiquidDiffract/resources/hubbel_compton/Br.npy
LiquidDiffract/resources/hubbel_compton/C.npy
LiquidDiffract/resources/hubbel_compton/Ca.npy
LiquidDiffract/resources/hubbel_compton/Cd.npy
LiquidDiffract/resources/hubbel_compton/Ce.npy
LiquidDiffract/resources/hubbel_compton/Cf.npy
LiquidDiffract/resources/hubbel_compton/Cl.npy
LiquidDiffract/resources/hubbel_compton/Cm.npy
LiquidDiffract/resources/hubbel_compton/Co.npy
LiquidDiffract-1.2.5.dist-info/LICENSE
LiquidDiffract-1.2.5.dist-info/METADATA
LiquidDiffract-1.2.5.dist-info/WHEEL
LiquidDiffract-1.2.5.dist-info/entry_points.txt
LiquidDiffract-1.2.5.dist-info/top_level.txt
LiquidDiffract-1.2.5.dist-info/zip-safe
LiquidDiffract-1.2.5.dist-info/RECORD
