Metadata-Version: 2.1
Name: LiquidDiffract
Version: 1.2.5
Summary: Liquid structure/total X-ray scattering analysis
Home-page: https://github.com/bjheinen/LiquidDiffract
Author: Benedict J Heinen
Author-email: benedict.heinen@gmail.com
License: GPL
Requires-Python: >=3.8
License-File: LICENSE
Requires-Dist: numpy >=1.20.0
Requires-Dist: scipy >=1.6.0
Requires-Dist: PyQt6 >=6.2.0
Requires-Dist: qtpy >=2.3.0
Requires-Dist: pyqtgraph >=0.13.0
Requires-Dist: lmfit >=1.0.2
Requires-Dist: packaging >=14.1
Requires-Dist: importlib-resources ; python_version < "3.9"
